{
  "name": "n8n-mcp",
  "version": "3.0.0",
  "description": "n8n MCP Server - Lightweight runtime (pre-built database required)",
  "main": "dist/index.js",
  "author": "Romuald Czlonkowski @ www.aiadvisors.pl/en",
  "license": "MIT",
  "dependencies": {
    "@modelcontextprotocol/sdk": "^1.13.2",
    "axios": "^1.10.0",
    "dotenv": "^16.5.0",
    "express": "^5.1.0",
    "express-rate-limit": "^7.4.1",
    "helmet": "^8.0.0",
    "sql.js": "^1.13.0",
    "uuid": "^10.0.0",
    "zod": "^3.23.8"
  },
  "engines": {
    "node": ">=18.0.0"
  },
  "repository": {
    "type": "git",
    "url": "git+https://github.com/Zevas1993/One-Stop-Shop-N8N-MCP.git"
  },
  "keywords": [
    "n8n",
    "mcp",
    "model-context-protocol",
    "ai",
    "workflow",
    "automation",
    "lightweight"
  ]
}
