[
  {
    "config": "Config 1: Just triggers",
    "status": "SUCCESS",
    "id": "08YXRklsyxOLUAOj",
    "nodeCount": 2
  },
  {
    "config": "Config 2: Triggers + Set nodes",
    "status": "SUCCESS",
    "id": "zO20RKI7WzMsbhIy",
    "nodeCount": 5
  },
  {
    "config": "Config 3: Add basic operations",
    "status": "SUCCESS",
    "id": "rdgPF8iDvAP1zmPs",
    "nodeCount": 8
  },
  {
    "config": "Config 4: Add AI nodes (no connections yet)",
    "status": "SUCCESS",
    "id": "HbhAPH5RrJuv4NgR",
    "nodeCount": 12
  },
  {
    "config": "Config 5: Add all AI support nodes",
    "status": "SUCCESS",
    "id": "ri7EQJFYBt83wsZZ",
    "nodeCount": 16
  },
  {
    "config": "Config 6: Add processing nodes",
    "status": "SUCCESS",
    "id": "68q3C6E2L3SrVmyu",
    "nodeCount": 20
  },
  {
    "config": "Config 7: Add response nodes",
    "status": "SUCCESS",
    "id": "7zR6pzvyJGR6kqPS",
    "nodeCount": 21
  }
]